[
    {
        "displayName": "Spike",
        "type": "character",
        "key": "spike",
        "index": 0,
        "rarity": 0,
        "weight": 90,
        "cost": 0,
        "stack": 1,
        "maxCount": -1,
        "description": "Unlocks Spike for one challenge."
    },
    {
        "displayName": "Gus",
        "type": "character",
        "key": "gus",
        "index": 1,
        "rarity": 0,
        "weight": 90,
        "cost": 0,
        "stack": 1,
        "maxCount": -1,
        "description": "Unlocks Gus for one challenge."
    },
    {
        "displayName": "Emz",
        "type": "character",
        "key": "emz",
        "index": 2,
        "rarity": 0,
        "weight": 90,
        "cost": 0,
        "stack": 1,
        "maxCount": -1,
        "description": "Unlocks Emz for one challenge."
    },
    {
        "displayName": "Darryl",
        "type": "character",
        "key": "darryl",
        "index": 3,
        "rarity": 0,
        "weight": 90,
        "cost": 0,
        "stack": 1,
        "maxCount": -1,
        "description": "Unlocks Darryl for one challenge."
    },
    {
        "displayName": "Tara",
        "type": "character",
        "key": "tara",
        "index": 4,
        "rarity": 1,
        "weight": 100,
        "cost": 0,
        "stack": 1,
        "maxCount": -1,
        "description": "Unlocks Tara for one challenge."
    },
    {
        "displayName": "Piper",
        "type": "character",
        "key": "piper",
        "index": 5,
        "rarity": 1,
        "weight": 100,
        "cost": 0,
        "stack": 1,
        "maxCount": -1,
        "description": "Unlocks Piper for one challenge."
    },
    {
        "displayName": "Lily",
        "type": "character",
        "key": "lily",
        "index": 6,
        "rarity": 1,
        "weight": 100,
        "cost": 0,
        "stack": 1,
        "maxCount": -1,
        "description": "Unlocks Lily for one challenge."
    },
    {
        "displayName": "Stu",
        "type": "character",
        "key": "stu",
        "index": 7,
        "rarity": 2,
        "weight": 114,
        "cost": 0,
        "stack": 1,
        "maxCount": -1,
        "description": "Unlocks Stu for one challenge."
    },
    {
        "displayName": "Maisie",
        "type": "character",
        "key": "maisie",
        "index": 8,
        "rarity": 2,
        "weight": 114,
        "cost": 0,
        "stack": 1,
        "maxCount": -1,
        "description": "Unlocks Maisie for one challenge."
    },
    {
        "displayName": "Shade",
        "type": "character",
        "key": "shade",
        "index": 9,
        "rarity": 3,
        "weight": 78,
        "cost": 0,
        "stack": 1,
        "maxCount": -1,
        "description": "Unlocks Shade for one challenge."
    },
    {
        "displayName": "Mandy",
        "type": "character",
        "key": "mandy",
        "index": 10,
        "rarity": 3,
        "weight": 78,
        "cost": 0,
        "stack": 1,
        "maxCount": -1,
        "description": "Unlocks Mandy for one challenge."
    },
    {
        "displayName": "Hank",
        "type": "character",
        "key": "hank",
        "index": 11,
        "rarity": 4,
        "weight": 60,
        "cost": 0,
        "stack": 1,
        "maxCount": -1,
        "description": "Unlocks Hank for one challenge."
    },
    {
        "displayName": "Speed Increase",
        "type": "powerup",
        "key": "powerup1",
        "index": 0,
        "rarity": 0,
        "weight": 180,
        "cost": 0,
        "stack": 1,
        "maxCount": -1,
        "description": "Increases speed by 2."
    },
    {
        "displayName": "Super Charge Increase",
        "type": "powerup",
        "key": "powerup2",
        "index": 1,
        "rarity": 0,
        "weight": 180,
        "cost": 0,
        "stack": 1,
        "maxCount": -1,
        "description": "Increases base super charge by 30%."
    },
    {
        "displayName": "Temporary Tier Up",
        "type": "powerup",
        "key": "powerup3",
        "index": 2,
        "rarity": 0,
        "weight": 180,
        "cost": 0,
        "stack": 1,
        "maxCount": -1,
        "description": "All brawlers' tiers are set to your highest brawler's tier."
    },
    {
        "displayName": "All Star Powers",
        "type": "powerup",
        "key": "powerup4",
        "index": 3,
        "rarity": 1,
        "weight": 150,
        "cost": 0,
        "stack": 1,
        "maxCount": -1,
        "description": "Unlocks all star powers on the currently selected brawler."
    },
    {
        "displayName": "All Gears",
        "type": "powerup",
        "key": "powerup5",
        "index": 4,
        "rarity": 1,
        "weight": 150,
        "cost": 0,
        "stack": 1,
        "maxCount": -1,
        "description": "Unlocks all gears on the currently selected brawler."
    },
    {
        "displayName": "Weaker Enemies",
        "type": "powerup",
        "key": "powerup6",
        "index": 5,
        "rarity": 1,
        "weight": 150,
        "cost": 0,
        "stack": 1,
        "maxCount": -1,
        "description": "Enemy health and damage are decreased by 5%."
    },
    {
        "displayName": "Easier Speed Score",
        "type": "powerup",
        "key": "powerup7",
        "index": 6,
        "rarity": 2,
        "weight": 114,
        "cost": 0,
        "stack": 1,
        "maxCount": -1,
        "description": "The speed score has a 40% longer time limit."
    },
    {
        "displayName": "Easier Health Bonus Score",
        "type": "powerup",
        "key": "powerup8",
        "index": 7,
        "rarity": 2,
        "weight": 114,
        "cost": 0,
        "stack": 1,
        "maxCount": -1,
        "description": "The health bonus score has a 30% lower health requirement."
    },
    {
        "displayName": "Duplicate Brawler",
        "type": "powerup",
        "key": "powerup9",
        "index": 8,
        "rarity": 2,
        "weight": 114,
        "cost": 0,
        "stack": 1,
        "maxCount": -1,
        "description": "The currently selected brawler can be used again in the next challenge."
    },
    {
        "displayName": "Longer Spawn Delay",
        "type": "powerup",
        "key": "powerup10",
        "index": 9,
        "rarity": 3,
        "weight": 117,
        "cost": 0,
        "stack": 1,
        "maxCount": -1,
        "description": "Increases time between enemy waves by 50%."
    },
    {
        "displayName": "Extra Life",
        "type": "powerup",
        "key": "powerup11",
        "index": 10,
        "rarity": 3,
        "weight": 117,
        "cost": 0,
        "stack": 1,
        "maxCount": -1,
        "description": "Activates when losing a challenge, allowing you to retry. Converted to 20 credits if unused."
    },
    {
        "displayName": "Duplicate Accessories",
        "type": "powerup",
        "key": "powerup12",
        "index": 11,
        "rarity": 4,
        "weight": 90,
        "cost": 0,
        "stack": 1,
        "maxCount": -1,
        "description": "All selected accessories can be used again in the next challenge."
    },
    {
        "displayName": "Power Points",
        "type": "resource",
        "key": "power",
        "index": -1,
        "rarity": 0,
        "weight": 270,
        "cost": 0,
        "stack": 4,
        "maxCount": -1,
        "description": "Use these to upgrade stats between levels."
    },
    {
        "displayName": "Power Points",
        "type": "resource",
        "key": "power",
        "index": -1,
        "rarity": 1,
        "weight": 225,
        "cost": 0,
        "stack": 6,
        "maxCount": -1,
        "description": "Use these to upgrade stats between levels."
    },
    {
        "displayName": "Power Points",
        "type": "resource",
        "key": "power",
        "index": -1,
        "rarity": 2,
        "weight": 114,
        "cost": 0,
        "stack": 10,
        "maxCount": -1,
        "description": "Use these to upgrade stats between levels."
    },
    {
        "displayName": "Power Points",
        "type": "resource",
        "key": "power",
        "index": -1,
        "rarity": 3,
        "weight": 78,
        "cost": 0,
        "stack": 20,
        "maxCount": -1,
        "description": "Use these to upgrade stats between levels."
    },
    {
        "displayName": "Power Points",
        "type": "resource",
        "key": "power",
        "index": -1,
        "rarity": 4,
        "weight": 45,
        "cost": 0,
        "stack": 60,
        "maxCount": -1,
        "description": "Use these to upgrade stats between levels."
    },
    {
        "displayName": "Gear Scrap",
        "type": "resource",
        "key": "gears",
        "index": -1,
        "rarity": 0,
        "weight": 270,
        "cost": 0,
        "stack": 1,
        "maxCount": -1,
        "description": "Use these to activate Gears."
    },
    {
        "displayName": "Gear Scrap",
        "type": "resource",
        "key": "gears",
        "index": -1,
        "rarity": 1,
        "weight": 225,
        "cost": 0,
        "stack": 2,
        "maxCount": -1,
        "description": "Use these to activate Gears."
    },
    {
        "displayName": "Gear Scrap",
        "type": "resource",
        "key": "gears",
        "index": -1,
        "rarity": 2,
        "weight": 114,
        "cost": 0,
        "stack": 3,
        "maxCount": -1,
        "description": "Use these to activate Gears."
    },
    {
        "displayName": "Gear Scrap",
        "type": "resource",
        "key": "gears",
        "index": -1,
        "rarity": 3,
        "weight": 78,
        "cost": 0,
        "stack": 5,
        "maxCount": -1,
        "description": "Use these to activate Gears."
    },
    {
        "displayName": "Accessory Tokens",
        "type": "resource",
        "key": "accessories",
        "index": -1,
        "rarity": 2,
        "weight": 114,
        "cost": 0,
        "stack": 1,
        "maxCount": -1,
        "description": "Increases the maximum accessories usable per challenge."
    },
    {
        "displayName": "Accessory Tokens",
        "type": "resource",
        "key": "accessories",
        "index": -1,
        "rarity": 3,
        "weight": 78,
        "cost": 0,
        "stack": 2,
        "maxCount": -1,
        "description": "Increases the maximum accessories usable per challenge."
    },
    {
        "displayName": "Accessory Tokens",
        "type": "resource",
        "key": "accessories",
        "index": -1,
        "rarity": 4,
        "weight": 45,
        "cost": 0,
        "stack": 6,
        "maxCount": -1,
        "description": "Increases the maximum accessories usable per challenge."
    },
    {
        "displayName": "Supply Drop",
        "type": "accessory",
        "key": "default1",
        "index": 0,
        "rarity": 0,
        "weight": 72,
        "cost": 3,
        "stack": 1,
        "maxCount": -1,
        "description": "Increases health and damage."
    },
    {
        "displayName": "Green Supply Drop",
        "type": "accessory",
        "key": "default2",
        "index": 1,
        "rarity": 0,
        "weight": 72,
        "cost": 4,
        "stack": 1,
        "maxCount": -1,
        "description": "Increases health and damage."
    },
    {
        "displayName": "Red Supply Drop",
        "type": "accessory",
        "key": "default3",
        "index": 2,
        "rarity": 0,
        "weight": 72,
        "cost": 4,
        "stack": 1,
        "maxCount": -1,
        "description": "Increases health and damage."
    },
    {
        "displayName": "Defensive Potion",
        "type": "accessory",
        "key": "default4",
        "index": 3,
        "rarity": 0,
        "weight": 72,
        "cost": 4,
        "stack": 1,
        "maxCount": -1,
        "description": "Increases health and healing."
    },
    {
        "displayName": "Healing Potion",
        "type": "accessory",
        "key": "shop1",
        "index": 4,
        "rarity": 0,
        "weight": 72,
        "cost": 5,
        "stack": 1,
        "maxCount": -1,
        "description": "Increases healing."
    },
    {
        "displayName": "Life Steal Potion",
        "type": "accessory",
        "key": "shop2",
        "index": 5,
        "rarity": 0,
        "weight": 72,
        "cost": 5,
        "stack": 1,
        "maxCount": -1,
        "description": "Increases life steal."
    },
    {
        "displayName": "Offensive Potion",
        "type": "accessory",
        "key": "default5",
        "index": 6,
        "rarity": 0,
        "weight": 72,
        "cost": 4,
        "stack": 1,
        "maxCount": -1,
        "description": "Increases damage and critical damage."
    },
    {
        "displayName": "Speed Potion",
        "type": "accessory",
        "key": "shop3",
        "index": 7,
        "rarity": 0,
        "weight": 72,
        "cost": 5,
        "stack": 1,
        "maxCount": -1,
        "description": "Increases critical damage."
    },
    {
        "displayName": "Combo Potion",
        "type": "accessory",
        "key": "shop4",
        "index": 8,
        "rarity": 0,
        "weight": 72,
        "cost": 5,
        "stack": 1,
        "maxCount": -1,
        "description": "Increases combo damage."
    },
    {
        "displayName": "Neon Light",
        "type": "accessory",
        "key": "retropolis",
        "index": 9,
        "rarity": 0,
        "weight": 72,
        "cost": 4,
        "stack": 1,
        "maxCount": -1,
        "description": "Fire damage and damage marks from enemies are less effective."
    },
    {
        "displayName": "Iron Wall",
        "type": "accessory",
        "key": "shop5",
        "index": 10,
        "rarity": 0,
        "weight": 72,
        "cost": 4,
        "stack": 1,
        "maxCount": -1,
        "description": "Knockbacks and slows from enemies are less effective."
    },
    {
        "displayName": "Finx's Time Staff",
        "type": "accessory",
        "key": "shop8",
        "index": 11,
        "rarity": 0,
        "weight": 72,
        "cost": 4,
        "stack": 1,
        "maxCount": -1,
        "description": "Increases projectile speed."
    },
    {
        "displayName": "Nani's Drone",
        "type": "accessory",
        "key": "shop7",
        "index": 12,
        "rarity": 0,
        "weight": 72,
        "cost": 4,
        "stack": 1,
        "maxCount": -1,
        "description": "Increases attack range."
    },
    {
        "displayName": "Buster's Projector",
        "type": "accessory",
        "key": "brawlbox6",
        "index": 13,
        "rarity": 0,
        "weight": 72,
        "cost": 4,
        "stack": 1,
        "maxCount": -1,
        "description": "The super charges faster when not attacking."
    },
    {
        "displayName": "Bling Stack",
        "type": "accessory",
        "key": "noupgrades",
        "index": 14,
        "rarity": 0,
        "weight": 72,
        "cost": 3,
        "stack": 1,
        "maxCount": -1,
        "description": "Receive 1 extra gear scrap when completing a level."
    },
    {
        "displayName": "Shelly's Shotgun",
        "type": "accessory",
        "key": "shelly",
        "index": 15,
        "rarity": 0,
        "weight": 72,
        "cost": 3,
        "stack": 1,
        "maxCount": -1,
        "description": "Deal more damage to and receive more protection from Damage Dealer enemies."
    },
    {
        "displayName": "R-T's Camera",
        "type": "accessory",
        "key": "rt",
        "index": 16,
        "rarity": 0,
        "weight": 72,
        "cost": 3,
        "stack": 1,
        "maxCount": -1,
        "description": "Deal more damage to and receive more protection from Controller enemies."
    },
    {
        "displayName": "El Primo's Belt",
        "type": "accessory",
        "key": "elprimo",
        "index": 17,
        "rarity": 0,
        "weight": 72,
        "cost": 3,
        "stack": 1,
        "maxCount": -1,
        "description": "Deal more damage to and receive more protection from Tank enemies."
    },
    {
        "displayName": "8-Bit's Turret",
        "type": "accessory",
        "key": "8bit",
        "index": 18,
        "rarity": 0,
        "weight": 72,
        "cost": 3,
        "stack": 1,
        "maxCount": -1,
        "description": "Receive more protection from Damage Dealer enemies."
    },
    {
        "displayName": "Jessie's Backpack",
        "type": "accessory",
        "key": "jessie",
        "index": 19,
        "rarity": 0,
        "weight": 72,
        "cost": 3,
        "stack": 1,
        "maxCount": -1,
        "description": "Receive more protection from Controller enemies."
    },
    {
        "displayName": "Jacky's Drill",
        "type": "accessory",
        "key": "jacky",
        "index": 20,
        "rarity": 0,
        "weight": 72,
        "cost": 3,
        "stack": 1,
        "maxCount": -1,
        "description": "Receive more protection from Tank enemies."
    },
    {
        "displayName": "Colt's Revolvers",
        "type": "accessory",
        "key": "colt",
        "index": 21,
        "rarity": 0,
        "weight": 72,
        "cost": 3,
        "stack": 1,
        "maxCount": -1,
        "description": "Receive more protection from Marksman enemies."
    },
    {
        "displayName": "Mortis's Shovel",
        "type": "accessory",
        "key": "mortis",
        "index": 22,
        "rarity": 0,
        "weight": 72,
        "cost": 3,
        "stack": 1,
        "maxCount": -1,
        "description": "Receive more protection from Assassin enemies."
    },
    {
        "displayName": "Colette's Scrapbook",
        "type": "accessory",
        "key": "colette",
        "index": 23,
        "rarity": 0,
        "weight": 72,
        "cost": 3,
        "stack": 1,
        "maxCount": -1,
        "description": "Deal more damage to Damage Dealer enemies."
    },
    {
        "displayName": "Eve's Spaceship",
        "type": "accessory",
        "key": "eve",
        "index": 24,
        "rarity": 0,
        "weight": 72,
        "cost": 3,
        "stack": 1,
        "maxCount": -1,
        "description": "Deal more damage to Controller enemies."
    },
    {
        "displayName": "Frank's Hammer",
        "type": "accessory",
        "key": "frank",
        "index": 25,
        "rarity": 0,
        "weight": 72,
        "cost": 3,
        "stack": 1,
        "maxCount": -1,
        "description": "Deal more damage to Tank enemies."
    },
    {
        "displayName": "Belle's Rifle",
        "type": "accessory",
        "key": "belle",
        "index": 26,
        "rarity": 0,
        "weight": 72,
        "cost": 3,
        "stack": 1,
        "maxCount": -1,
        "description": "Deal more damage to Marksman enemies."
    },
    {
        "displayName": "Leon's Lollipop",
        "type": "accessory",
        "key": "leon",
        "index": 27,
        "rarity": 0,
        "weight": 72,
        "cost": 3,
        "stack": 1,
        "maxCount": -1,
        "description": "Deal more damage to Assassin enemies."
    },
    {
        "displayName": "Bronze Medal",
        "type": "accessory",
        "key": "mastery1",
        "index": 28,
        "rarity": 0,
        "weight": 72,
        "cost": 3,
        "stack": 1,
        "maxCount": -1,
        "description": "Gain more coins from rewards and receive more items from Brawl Boxes."
    },
    {
        "displayName": "Silver Medal",
        "type": "accessory",
        "key": "mastery2",
        "index": 29,
        "rarity": 0,
        "weight": 72,
        "cost": 3,
        "stack": 1,
        "maxCount": -1,
        "description": "Gain more coins from rewards and receive more items from Brawl Boxes."
    },
    {
        "displayName": "Poco's Guitar",
        "type": "accessory",
        "key": "nodamage",
        "index": 30,
        "rarity": 1,
        "weight": 72,
        "cost": 5,
        "stack": 1,
        "maxCount": -1,
        "description": "Increases healing when not attacking."
    },
    {
        "displayName": "Meeple's Dice",
        "type": "accessory",
        "key": "usecombo",
        "index": 31,
        "rarity": 1,
        "weight": 72,
        "cost": 5,
        "stack": 1,
        "maxCount": -1,
        "description": "Increases charge rate of the combo."
    },
    {
        "displayName": "Train Tickets",
        "type": "accessory",
        "key": "ghoststation",
        "index": 32,
        "rarity": 1,
        "weight": 72,
        "cost": 5,
        "stack": 1,
        "maxCount": -1,
        "description": "Receive more power points when completing a level."
    },
    {
        "displayName": "Barley's Bottle",
        "type": "accessory",
        "key": "oldtown",
        "index": 33,
        "rarity": 1,
        "weight": 72,
        "cost": 5,
        "stack": 1,
        "maxCount": -1,
        "description": "After not taking damage for a few seconds, get a shield."
    },
    {
        "displayName": "Clancy's Tokens",
        "type": "accessory",
        "key": "deepsea",
        "index": 34,
        "rarity": 1,
        "weight": 72,
        "cost": 5,
        "stack": 1,
        "maxCount": -1,
        "description": "Using the super increases life steal for the rest of the level."
    },
    {
        "displayName": "Charlie's Cocoon",
        "type": "accessory",
        "key": "nomove",
        "index": 35,
        "rarity": 1,
        "weight": 72,
        "cost": 5,
        "stack": 1,
        "maxCount": -1,
        "description": "When at low health, receive more protection."
    },
    {
        "displayName": "Doug's Hot Dog",
        "type": "accessory",
        "key": "brawlbox3",
        "index": 36,
        "rarity": 1,
        "weight": 72,
        "cost": 5,
        "stack": 1,
        "maxCount": -1,
        "description": "Once in a while when at low health, heal to full health."
    },
    {
        "displayName": "Rosa's Gloves",
        "type": "accessory",
        "key": "biodome",
        "index": 37,
        "rarity": 1,
        "weight": 72,
        "cost": 5,
        "stack": 1,
        "maxCount": -1,
        "description": "Increases critical chance when close to maximum health."
    },
    {
        "displayName": "Starr Candy",
        "type": "accessory",
        "key": "candyland",
        "index": 38,
        "rarity": 1,
        "weight": 72,
        "cost": 5,
        "stack": 1,
        "maxCount": -1,
        "description": "When defeating an enemy, gain speed for a few seconds."
    },
    {
        "displayName": "Surge's Energy Drink",
        "type": "accessory",
        "key": "supercity",
        "index": 39,
        "rarity": 1,
        "weight": 72,
        "cost": 5,
        "stack": 1,
        "maxCount": -1,
        "description": "For the first few seconds of each level, gain speed and damage."
    },
    {
        "displayName": "Angelo's Bow",
        "type": "accessory",
        "key": "brawlbox4",
        "index": 40,
        "rarity": 1,
        "weight": 72,
        "cost": 5,
        "stack": 1,
        "maxCount": -1,
        "description": "Attacks deal extra damage every second for a few seconds."
    },
    {
        "displayName": "Fang's Shoe",
        "type": "accessory",
        "key": "fastwin",
        "index": 41,
        "rarity": 1,
        "weight": 72,
        "cost": 5,
        "stack": 1,
        "maxCount": -1,
        "description": "When defeating an enemy, partially recharge the super."
    },
    {
        "displayName": "Super Juice",
        "type": "accessory",
        "key": "brawlbox7",
        "index": 42,
        "rarity": 1,
        "weight": 72,
        "cost": 5,
        "stack": 1,
        "maxCount": -1,
        "description": "The super charges past a full charge."
    },
    {
        "displayName": "Pearl's Cookie",
        "type": "accessory",
        "key": "pearl",
        "index": 43,
        "rarity": 1,
        "weight": 72,
        "cost": 4,
        "stack": 1,
        "maxCount": -1,
        "description": "Receive more protection from Damage Dealer enemies."
    },
    {
        "displayName": "Mr. P's Suitcase",
        "type": "accessory",
        "key": "mrp",
        "index": 44,
        "rarity": 1,
        "weight": 72,
        "cost": 4,
        "stack": 1,
        "maxCount": -1,
        "description": "Receive more protection from Controller enemies."
    },
    {
        "displayName": "Bibi's Bat",
        "type": "accessory",
        "key": "bibi",
        "index": 45,
        "rarity": 1,
        "weight": 72,
        "cost": 4,
        "stack": 1,
        "maxCount": -1,
        "description": "Receive more protection from Tank enemies."
    },
    {
        "displayName": "Bea's Bee",
        "type": "accessory",
        "key": "bea",
        "index": 46,
        "rarity": 1,
        "weight": 72,
        "cost": 4,
        "stack": 1,
        "maxCount": -1,
        "description": "Receive more protection from Marksman enemies."
    },
    {
        "displayName": "Melodie's Note",
        "type": "accessory",
        "key": "melodie",
        "index": 47,
        "rarity": 1,
        "weight": 72,
        "cost": 4,
        "stack": 1,
        "maxCount": -1,
        "description": "Receive more protection from Assassin enemies."
    },
    {
        "displayName": "Chester's Box",
        "type": "accessory",
        "key": "chester",
        "index": 48,
        "rarity": 1,
        "weight": 72,
        "cost": 4,
        "stack": 1,
        "maxCount": -1,
        "description": "Deal more damage to Damage Dealer enemies."
    },
    {
        "displayName": "Bo's Quiver",
        "type": "accessory",
        "key": "bo",
        "index": 49,
        "rarity": 1,
        "weight": 72,
        "cost": 4,
        "stack": 1,
        "maxCount": -1,
        "description": "Deal more damage to Controller enemies."
    },
    {
        "displayName": "Ollie's Skateboard",
        "type": "accessory",
        "key": "ollie",
        "index": 50,
        "rarity": 1,
        "weight": 72,
        "cost": 4,
        "stack": 1,
        "maxCount": -1,
        "description": "Deal more damage to Tank enemies."
    },
    {
        "displayName": "Brock's Rocket Launcher",
        "type": "accessory",
        "key": "brock",
        "index": 51,
        "rarity": 1,
        "weight": 72,
        "cost": 4,
        "stack": 1,
        "maxCount": -1,
        "description": "Deal more damage to Marksman enemies."
    },
    {
        "displayName": "Max's Energy Drink",
        "type": "accessory",
        "key": "max",
        "index": 52,
        "rarity": 1,
        "weight": 72,
        "cost": 4,
        "stack": 1,
        "maxCount": -1,
        "description": "Deal more damage to Assassin enemies."
    },
    {
        "displayName": "Gold Medal",
        "type": "accessory",
        "key": "mastery3",
        "index": 53,
        "rarity": 1,
        "weight": 72,
        "cost": 4,
        "stack": 1,
        "maxCount": -1,
        "description": "Gain more coins from rewards and receive more items from Brawl Boxes."
    },
    {
        "displayName": "Diamond Medal",
        "type": "accessory",
        "key": "mastery4",
        "index": 54,
        "rarity": 1,
        "weight": 72,
        "cost": 4,
        "stack": 1,
        "maxCount": -1,
        "description": "Gain more coins from rewards and receive more items from Brawl Boxes."
    },
    {
        "displayName": "Gift Shop Shirt",
        "type": "accessory",
        "key": "giftshop",
        "index": 55,
        "rarity": 2,
        "weight": 72,
        "cost": 6,
        "stack": 1,
        "maxCount": -1,
        "description": "Increases health, critical damage, and life steal."
    },
    {
        "displayName": "Nita's Bear Hat",
        "type": "accessory",
        "key": "rumblejungle",
        "index": 56,
        "rarity": 2,
        "weight": 72,
        "cost": 6,
        "stack": 1,
        "maxCount": -1,
        "description": "Increases damage, healing, and combo damage."
    },
    {
        "displayName": "Pam's Healing Station",
        "type": "accessory",
        "key": "shop6",
        "index": 57,
        "rarity": 2,
        "weight": 72,
        "cost": 6,
        "stack": 1,
        "maxCount": -1,
        "description": "Increases protection."
    },
    {
        "displayName": "Bull's Shotgun",
        "type": "accessory",
        "key": "wins",
        "index": 58,
        "rarity": 2,
        "weight": 72,
        "cost": 6,
        "stack": 1,
        "maxCount": -1,
        "description": "Increases attack reload."
    },
    {
        "displayName": "Janet's Microphone",
        "type": "accessory",
        "key": "stuntshow",
        "index": 59,
        "rarity": 2,
        "weight": 72,
        "cost": 6,
        "stack": 1,
        "maxCount": -1,
        "description": "Increases charge rate of the super."
    },
    {
        "displayName": "Healing Skull",
        "type": "accessory",
        "key": "brawlbox1",
        "index": 60,
        "rarity": 2,
        "weight": 72,
        "cost": 6,
        "stack": 1,
        "maxCount": -1,
        "description": "When defeating an enemy, restore some health."
    },
    {
        "displayName": "Sam's Knuckle Busters",
        "type": "accessory",
        "key": "brawlbox2",
        "index": 61,
        "rarity": 2,
        "weight": 72,
        "cost": 6,
        "stack": 1,
        "maxCount": -1,
        "description": "Every few seconds, restore some missing health."
    },
    {
        "displayName": "Mysterious Mushroom",
        "type": "accessory",
        "key": "enchantedforest",
        "index": 62,
        "rarity": 2,
        "weight": 72,
        "cost": 6,
        "stack": 1,
        "maxCount": -1,
        "description": "Every few seconds, heal health for each hit recently received."
    },
    {
        "displayName": "Arcade Machine",
        "type": "accessory",
        "key": "arcade",
        "index": 63,
        "rarity": 2,
        "weight": 72,
        "cost": 6,
        "stack": 1,
        "maxCount": -1,
        "description": "Defeating enemies increases damage for the rest of the level."
    },
    {
        "displayName": "Power Skull",
        "type": "accessory",
        "key": "brawlbox5",
        "index": 64,
        "rarity": 2,
        "weight": 72,
        "cost": 6,
        "stack": 1,
        "maxCount": -1,
        "description": "When defeating an enemy, increase the next attack's damage."
    },
    {
        "displayName": "Cursed Book",
        "type": "accessory",
        "key": "odditiesshop",
        "index": 65,
        "rarity": 2,
        "weight": 72,
        "cost": 6,
        "stack": 1,
        "maxCount": -1,
        "description": "The combo gains a speed and reload buff."
    },
    {
        "displayName": "Heist Safe",
        "type": "accessory",
        "key": "trials",
        "index": 66,
        "rarity": 2,
        "weight": 72,
        "cost": 6,
        "stack": 1,
        "maxCount": -1,
        "description": "Receiving damage charges the super."
    },
    {
        "displayName": "Amber's Fire Staff",
        "type": "accessory",
        "key": "amber",
        "index": 67,
        "rarity": 2,
        "weight": 72,
        "cost": 5,
        "stack": 1,
        "maxCount": -1,
        "description": "Deal more damage to and receive more protection from Damage Dealer enemies."
    },
    {
        "displayName": "Lola's Scarf",
        "type": "accessory",
        "key": "lola",
        "index": 68,
        "rarity": 2,
        "weight": 72,
        "cost": 5,
        "stack": 1,
        "maxCount": -1,
        "description": "Deal more damage to and receive more protection from Controller enemies."
    },
    {
        "displayName": "Meg's Mech",
        "type": "accessory",
        "key": "meg",
        "index": 69,
        "rarity": 2,
        "weight": 72,
        "cost": 5,
        "stack": 1,
        "maxCount": -1,
        "description": "Deal more damage to and receive more protection from Tank enemies."
    },
    {
        "displayName": "Bonnie's Cannon",
        "type": "accessory",
        "key": "bonnie",
        "index": 70,
        "rarity": 2,
        "weight": 72,
        "cost": 5,
        "stack": 1,
        "maxCount": -1,
        "description": "Deal more damage to and receive more protection from Marksman enemies."
    },
    {
        "displayName": "Kaze's Fan",
        "type": "accessory",
        "key": "kaze",
        "index": 71,
        "rarity": 2,
        "weight": 72,
        "cost": 5,
        "stack": 1,
        "maxCount": -1,
        "description": "Deal more damage to and receive more protection from Assassin enemies."
    },
    {
        "displayName": "Amethyst Medal",
        "type": "accessory",
        "key": "mastery5",
        "index": 72,
        "rarity": 2,
        "weight": 72,
        "cost": 5,
        "stack": 1,
        "maxCount": -1,
        "description": "Gain more coins from rewards and receive more items from Brawl Boxes."
    },
    {
        "displayName": "Ruby Medal",
        "type": "accessory",
        "key": "mastery6",
        "index": 73,
        "rarity": 2,
        "weight": 72,
        "cost": 5,
        "stack": 1,
        "maxCount": -1,
        "description": "Gain more coins from rewards and receive more items from Brawl Boxes."
    },
    {
        "displayName": "Spike's Cactus",
        "type": "accessory",
        "key": "spike",
        "index": 74,
        "rarity": 3,
        "weight": 72,
        "cost": 2,
        "stack": 1,
        "maxCount": -1,
        "description": "All healing and damage buffs are increased when playing as Spike."
    },
    {
        "displayName": "Gus's Balloon",
        "type": "accessory",
        "key": "gus",
        "index": 75,
        "rarity": 3,
        "weight": 72,
        "cost": 2,
        "stack": 1,
        "maxCount": -1,
        "description": "All healing is increased when playing as Gus."
    },
    {
        "displayName": "Emz's Spray",
        "type": "accessory",
        "key": "emz",
        "index": 76,
        "rarity": 3,
        "weight": 72,
        "cost": 2,
        "stack": 1,
        "maxCount": -1,
        "description": "All damage buffs are stronger when playing as Emz."
    },
    {
        "displayName": "Darryl's Barrel",
        "type": "accessory",
        "key": "darryl",
        "index": 77,
        "rarity": 3,
        "weight": 72,
        "cost": 2,
        "stack": 1,
        "maxCount": -1,
        "description": "All healing is increased when playing as Darryl."
    },
    {
        "displayName": "Tara's Cards",
        "type": "accessory",
        "key": "tara",
        "index": 78,
        "rarity": 3,
        "weight": 72,
        "cost": 2,
        "stack": 1,
        "maxCount": -1,
        "description": "All healing is increased when playing as Tara."
    },
    {
        "displayName": "Piper's Umbrella",
        "type": "accessory",
        "key": "piper",
        "index": 79,
        "rarity": 3,
        "weight": 72,
        "cost": 2,
        "stack": 1,
        "maxCount": -1,
        "description": "All damage buffs are stronger when playing as Piper."
    },
    {
        "displayName": "Lily's Plant",
        "type": "accessory",
        "key": "lily",
        "index": 80,
        "rarity": 3,
        "weight": 72,
        "cost": 2,
        "stack": 1,
        "maxCount": -1,
        "description": "All damage buffs are stronger when playing as Lily."
    },
    {
        "displayName": "Stu's Wheel",
        "type": "accessory",
        "key": "stu",
        "index": 81,
        "rarity": 3,
        "weight": 72,
        "cost": 2,
        "stack": 1,
        "maxCount": -1,
        "description": "Super charges faster from all sources when playing as Stu."
    },
    {
        "displayName": "Maisie's Metal Arm",
        "type": "accessory",
        "key": "maisie",
        "index": 82,
        "rarity": 3,
        "weight": 72,
        "cost": 2,
        "stack": 1,
        "maxCount": -1,
        "description": "Super charges faster from all sources when playing as Maisie."
    },
    {
        "displayName": "Shade's Keychain",
        "type": "accessory",
        "key": "shade",
        "index": 83,
        "rarity": 3,
        "weight": 72,
        "cost": 2,
        "stack": 1,
        "maxCount": -1,
        "description": "All healing is increased when playing as Shade."
    },
    {
        "displayName": "Mandy's Candy Dispenser",
        "type": "accessory",
        "key": "mandy",
        "index": 84,
        "rarity": 3,
        "weight": 72,
        "cost": 2,
        "stack": 1,
        "maxCount": -1,
        "description": "All damage buffs are stronger when playing as Mandy."
    },
    {
        "displayName": "Hank's Helmet",
        "type": "accessory",
        "key": "hank",
        "index": 85,
        "rarity": 3,
        "weight": 72,
        "cost": 2,
        "stack": 1,
        "maxCount": -1,
        "description": "All healing and damage buffs are increased when playing as Hank."
    },
    {
        "displayName": "Citrine Medal",
        "type": "accessory",
        "key": "mastery7",
        "index": 86,
        "rarity": 3,
        "weight": 72,
        "cost": 6,
        "stack": 1,
        "maxCount": -1,
        "description": "Gain more coins from rewards and receive more items from Brawl Boxes."
    },
    {
        "displayName": "Championship Trophy",
        "type": "accessory",
        "key": "perfect1",
        "index": 87,
        "rarity": 4,
        "weight": 72,
        "cost": 7,
        "stack": 1,
        "maxCount": -1,
        "description": "Increases game score and all Brawl Boxes will be at maximum quality, regardless of score."
    },
    {
        "displayName": "Hypercharged Token",
        "type": "accessory",
        "key": "perfect2",
        "index": 88,
        "rarity": 4,
        "weight": 72,
        "cost": 7,
        "stack": 1,
        "maxCount": -1,
        "description": "Fully charges one Hypercharge and increases its charge rate during the next challenge."
    },
    {
        "displayName": "Omega Box",
        "type": "accessory",
        "key": "enemies",
        "index": 89,
        "rarity": 4,
        "weight": 72,
        "cost": 7,
        "stack": 1,
        "maxCount": -1,
        "description": "Gain more badges from rewards and unlock the option to open the Ultra Box."
    },
    {
        "displayName": "Starr Drop",
        "type": "accessory",
        "key": "challenges",
        "index": 90,
        "rarity": 4,
        "weight": 72,
        "cost": 7,
        "stack": 1,
        "maxCount": -1,
        "description": "Gain more mastery points from rewards and unlock the option to open the Ultra Box."
    },
    {
        "displayName": "Pro Medal",
        "type": "accessory",
        "key": "mastery8",
        "index": 91,
        "rarity": 4,
        "weight": 72,
        "cost": 7,
        "stack": 1,
        "maxCount": -1,
        "description": "Gain more coins from rewards and receive more items from Brawl Boxes."
    }
]